dependency_needle/__init__.py
dependency_needle/constants/__init__.py
dependency_needle/constants/constants.py
dependency_needle/container/__init__.py
dependency_needle/container/container.py
dependency_needle/container/interface_container.py
dependency_needle/dependency_strategy/__init__.py
dependency_needle/dependency_strategy/dependency_strategy_interface.py
dependency_needle/dependency_strategy/scoped_dependency_strategy.py
dependency_needle/dependency_strategy/singleton_dependency_strategy.py
dependency_needle/dependency_strategy/transient_dependency_strategy.py
dependency_needle/example/__init__.py
dependency_needle/example/example.py
dependency_needle/identifier_facade/__init__.py
dependency_needle/identifier_facade/identifier_facade.py
dependency_needle/lifetime_enums/__init__.py
dependency_needle/lifetime_enums/lifetime_enums.py
dependency_needle-2.1.0.dist-info/METADATA
dependency_needle-2.1.0.dist-info/WHEEL
dependency_needle-2.1.0.dist-info/top_level.txt
dependency_needle-2.1.0.dist-info/RECORD
