Metadata-Version: 2.4
Name: dependency_needle
Version: 2.1.0
Summary: Dependency injection container
Author: Abdelrahman Torky
Author-email: 24torky@gmail.com
Dynamic: author
Dynamic: author-email
Dynamic: summary
